tflite_runtime-2.5.0.post1.data/purelib/tflite_runtime/__init__.py
tflite_runtime-2.5.0.post1.data/purelib/tflite_runtime/_pywrap_tensorflow_interpreter_wrapper.cpython-37m-arm-linux-gnueabihf.so
tflite_runtime-2.5.0.post1.data/purelib/tflite_runtime/interpreter.py
tflite_runtime-2.5.0.post1.data/purelib/tflite_runtime/metrics_interface.py
tflite_runtime-2.5.0.post1.data/purelib/tflite_runtime/metrics_portable.py
tflrt-2.5.0.post1.dist-info/METADATA
tflrt-2.5.0.post1.dist-info/WHEEL
tflrt-2.5.0.post1.dist-info/top_level.txt
tflrt-2.5.0.post1.dist-info/RECORD
